{"betaground": 1, "fuori.dai.cliche": 1, "sometimes_the_same": 1, "gerard_estrany": 1, "nova_skinz": 1, "sidharth.singh": 1, "expressles": 1, "oyaiz": 1, "heidiemulder": 1, "natgeo.india1": 1, "heatherinah": 1, "konstantin_kaupp": 1, "moira.roadhouse.photography": 1, "sternthaldaniel": 1, "reverendsteveg": 1, "tombix45": 1, "blair.bare": 1, "hannahvivekphotography": 1, "lelllieee": 1, "yaufaio_o": 1, "benjaminatkins": 1, "mtphotog": 1, "pxa49": 1, "climbing_gym_cafe": 1, "facts_sauce": 1, "eduardode.sousa": 1, "mortenranners": 1, "jfit_18": 1, "backpackerbeginning": 1, "eckhardt_kuhn": 1, "white.moth": 1, "jwalkerasdf": 1, "goldenstateguiding": 1, "j_trvlr": 1, "the.luna.tails": 1, "running_lijn": 1, "dawnofthedave": 1, "alicecsun": 1, "bjrclimbing": 1, "sam_marfleet": 1, "sweet.olive.leigh": 1, "lostwithlolo": 1, "mike1o1d": 1, "alliance_fitness_n7": 1, "_viavii": 1, "hrh707": 1, "scottyd.1970": 1, "dani_strat": 1, "elmago_traveller": 1, "trailsportoutdoor": 1, "africandirk": 1, "dariolenglat": 1, "admanbellomy": 1, "vaudespain": 1, "isaac_passwater": 1, "nickoleep": 1, "julesnkc42": 1, "gs.personaltrainer": 1, "handsinthesky": 1, "clarice.gwyneth": 1, "khosasarbjeet": 1, "saki_tnm": 1, "jennyxinyi": 1, "ganja_guard": 1, "xenaandchance": 1, "daisygeorginapotter": 1, "ericarocks.jpg": 1, "meet.the.toms": 1, "honia.magierska": 1, "polesandproblems": 1, "lamarie_k": 1, "padstar_holds": 1, "sentiero_sisters": 1, "hand.pictures": 1, "theunknownexploration": 1, "distancefromthemoon": 1, "jeong._.soo": 1, "twodoorsdownboutiquega": 1, "elt.roy": 1, "a5ha": 1, "nostudioxl": 1, "suyentommasi_ph": 1, "anthea94_": 1, "veer10_": 1, "_ascender": 1, "pbrimagesoz": 1, "cairncolorado": 1, "maekimphotography": 1, "fededoblev": 1, "frida_vitis": 1, "fabhappyart": 1, "climbamt": 1, "ultrarunman.pl": 1, "melodieshandmade": 1, "onsomemountainoranother": 1, "sybyabraham": 1, "perpetualself": 1, "ausfirefighter": 1, "robertthered12": 1, "simonepetrazzi": 1, "harrisonized": 1, "illauddin_naziruddin": 1, "the_travel_pundit": 1, "chefrowley2612": 1, "out_and_wack": 1, "jowheel": 1, "artee_photography": 1, "kate_c1e": 1, "thoughtsonclimbing": 1, "see.ph": 1, "haraldgroiss": 1, "hananj912": 1, "nsprints": 1, "neues_leben_by_steffi": 1, "rmbillings": 1, "bangini7": 1, "travelers_ms": 1, "sevaless": 1, "tie.media": 1, "fannyadamsvintage": 1, "cyprusultra": 1, "daylight.stories": 1, "robertomoraschi": 1, "awefulll": 1, "anshh.rajput": 1, "layneysjewels": 1, "alishawanders": 1, "kodypruitt3": 1, "adventureclimb": 1, "mountain.somm": 1, "moroccotrail": 1, "sawyerbullock": 1, "m.a.r.e.n_m": 1, "mingpic_": 1, "plantpoweredpete": 1, "nakatchian": 1, "toadstoolgirl": 1, "ksunfedorova": 1, "max_cant_sit_in_one_place": 1, "imanibarathii": 1, "hongill": 1, "the.oxylus": 1, "bdubs_outdoorsaddict": 1, "lipseymediaconsulting": 1}